odoo/addons/account_invoice_custom_rounding/README.rst
odoo/addons/account_invoice_custom_rounding/__init__.py
odoo/addons/account_invoice_custom_rounding/__manifest__.py
odoo/addons/account_invoice_custom_rounding/i18n/account_invoice_custom_rounding.pot
odoo/addons/account_invoice_custom_rounding/models/__init__.py
odoo/addons/account_invoice_custom_rounding/models/account_move.py
odoo/addons/account_invoice_custom_rounding/models/account_move_line.py
odoo/addons/account_invoice_custom_rounding/models/account_tax.py
odoo/addons/account_invoice_custom_rounding/models/res_partner.py
odoo/addons/account_invoice_custom_rounding/readme/CONFIGURE.md
odoo/addons/account_invoice_custom_rounding/readme/DESCRIPTION.md
odoo/addons/account_invoice_custom_rounding/readme/USAGE.md
odoo/addons/account_invoice_custom_rounding/static/description/icon.png
odoo/addons/account_invoice_custom_rounding/static/description/index.html
odoo/addons/account_invoice_custom_rounding/tests/__init__.py
odoo/addons/account_invoice_custom_rounding/tests/common.py
odoo/addons/account_invoice_custom_rounding/tests/test_account_invoice_custom_rounding.py
odoo/addons/account_invoice_custom_rounding/views/account_move_views.xml
odoo/addons/account_invoice_custom_rounding/views/partner_view.xml
odoo_addon_account_invoice_custom_rounding-18.0.1.0.0.3.dist-info/METADATA
odoo_addon_account_invoice_custom_rounding-18.0.1.0.0.3.dist-info/WHEEL
odoo_addon_account_invoice_custom_rounding-18.0.1.0.0.3.dist-info/top_level.txt
odoo_addon_account_invoice_custom_rounding-18.0.1.0.0.3.dist-info/RECORD
